.coveragerc
.mailmap
.pylintrc
AUTHORS
CONTRIBUTING.rst
ChangeLog
HACKING.rst
LICENSE
MANIFEST.in
README.rst
babel.cfg
openstack-common.conf
requirements.txt
setup.cfg
setup.py
test-requirements.txt
tox.ini
doc/source/architecture.rst
doc/source/conf.py
doc/source/index.rst
doc/source/overview.rst
doc/source/_templates/sidebarlinks.html
doc/source/_theme_rtd/layout.html
doc/source/_theme_rtd/theme.conf
doc/source/devref/development.environment.rst
doc/source/devref/development.guidelines.rst
doc/source/devref/devstack.rst
doc/source/devref/edp.spi.rst
doc/source/devref/gerrit.rst
doc/source/devref/how_to_participate.rst
doc/source/devref/jenkins.rst
doc/source/devref/launchpad.rst
doc/source/devref/plugin.spi.rst
doc/source/devref/plugins.rst
doc/source/devref/quickstart.rst
doc/source/horizon/dashboard.user.guide.rst
doc/source/horizon/dev.environment.guide.rst
doc/source/horizon/installation.guide.rst
doc/source/images/hadoop-cluster-example.jpg
doc/source/images/hdp-plugin-architecture.png
doc/source/images/openstack-interop.png
doc/source/images/savanna-architecture.png
doc/source/userdoc/anti_affinity.rst
doc/source/userdoc/diskimagebuilder.rst
doc/source/userdoc/edp.rst
doc/source/userdoc/features.rst
doc/source/userdoc/hadoop-swift.rst
doc/source/userdoc/hdp_plugin.rst
doc/source/userdoc/installation.guide.rst
doc/source/userdoc/overview.rst
doc/source/userdoc/plugins.rst
doc/source/userdoc/python_client.rst
doc/source/userdoc/registering_image.rst
doc/source/userdoc/rest_api_v1.0.rst
doc/source/userdoc/rest_api_v1.1_EDP.rst
doc/source/userdoc/statuses.rst
doc/source/userdoc/vanilla_plugin.rst
etc/rest-api-samples/cluster_create_full.json
etc/rest-api-samples/cluster_create_minimal.json
etc/rest-api-samples/cluster_tmpl_create.json
etc/rest-api-samples/node_group_tmpl_create.json
etc/rest-api-samples/scale_cluster.json
etc/savanna/compute.topology.sample
etc/savanna/savanna.conf.sample
etc/savanna/savanna.conf.sample-full
etc/savanna/swift.topology.sample
savanna.egg-info/PKG-INFO
savanna.egg-info/SOURCES.txt
savanna.egg-info/dependency_links.txt
savanna.egg-info/entry_points.txt
savanna.egg-info/not-zip-safe
savanna.egg-info/requires.txt
savanna.egg-info/top_level.txt
