Metadata-Version: 1.0
Name: savanna
Version: 0.3
Summary: Savanna project
Home-page: https://savanna.readthedocs.org
Author: OpenStack
Author-email: openstack-dev@lists.openstack.org
License: Apache Software License
Platform: UNKNOWN
